[
  {
    "content": "Backend: add `origin` field to VisualArtIn model",
    "status": "completed"
  },
  {
    "content": "Admin schema: add Origin field + relabel Year→Chronology on Observatory form",
    "status": "completed"
  },
  {
    "content": "Observatory public page: relabel YEAR→CHRONOLOGY, show Origin in modal",
    "status": "completed"
  },
  {
    "content": "Symbols constellation: implement 3 groupings (Celestial/Wayfaring/Testimony), fix overlapping positions, scope hover lines to same-group only",
    "status": "completed"
  },
  {
    "content": "Verify with screenshots + esbuild",
    "status": "completed"
  }
]